{
  "project_info": {
    "project_number": "796583464221",
    "firebase_url": "https://fir-locatapptest1.firebaseio.com",
    "project_id": "fir-locatapptest1",
    "storage_bucket": "fir-locatapptest1.appspot.com"
  },
  "client": [
    {
      "client_info": {
        "mobilesdk_app_id": "1:796583464221:android:a196ddae0c5e39ec",
        "android_client_info": {
          "package_name": "gsoft.am.firebaselocatapptest1"
        }
      },
      "oauth_client": [
        {
          "client_id": "796583464221-so8hb57tui8p2053i9ue504kh0rto9d1.apps.googleusercontent.com",
          "client_type": 1,
          "android_info": {
            "package_name": "gsoft.am.firebaselocatapptest1",
            "certificate_hash": "8ba903449a10aa3eeb67d75753904c63d4ca99f6"
          }
        },
        {
          "client_id": "796583464221-g37pakghf6htsmaj43n9lv524i8m94oq.apps.googleusercontent.com",
          "client_type": 3
        }
      ],
      "api_key": [
        {
          "current_key": "AIzaSyDOdk8zTMzVgu_B2UqWKrhoHlzB2_GBkIA"
        }
      ],
      "services": {
        "analytics_service": {
          "status": 1
        },
        "appinvite_service": {
          "status": 2,
          "other_platform_oauth_client": [
            {
              "client_id": "796583464221-g37pakghf6htsmaj43n9lv524i8m94oq.apps.googleusercontent.com",
              "client_type": 3
            }
          ]
        },
        "ads_service": {
          "status": 2
        }
      }
    }
  ],
  "configuration_version": "1"
}